discord_progress_bar/__init__.py
discord_progress_bar/_version.py
discord_progress_bar/default_bars.py
discord_progress_bar/progress_bar.py
discord_progress_bar/py.typed
discord_progress_bar/types.py
discord_progress_bar-0.1.0a3.dist-info/METADATA
discord_progress_bar-0.1.0a3.dist-info/WHEEL
discord_progress_bar-0.1.0a3.dist-info/licenses/LICENSE
discord_progress_bar-0.1.0a3.dist-info/RECORD
