Metadata-Version: 2.4
Name: discord-progress-bar
Version: 0.1.0a3
Summary: A Python library for creating customizable progress bars with Discord emojis in your Discord bot messages.
Project-URL: Homepage, https://github.com/Paillat-dev/discord-progress-bar
Project-URL: source_archive, https://github.com/Paillat-dev/discord-progress-bar/archive/26f0f50aab3517672d5f5d8a7f5950cb32fae232.zip
Author-email: Paillat-dev <me@paillat.dev>
License-Expression: MIT
License-File: LICENSE
Keywords: bot,discord,emoji,emojis,progress-bar
Classifier: Development Status :: 3 - Alpha
Classifier: Intended Audience :: Developers
Classifier: License :: OSI Approved :: MIT License
Classifier: Operating System :: OS Independent
Classifier: Programming Language :: Python :: 3 :: Only
Classifier: Programming Language :: Python :: 3.12
Classifier: Typing :: Typed
Requires-Python: ==3.12.*
Requires-Dist: aiofile>=3.9.0
Requires-Dist: aiohttp>=3.11.18
Requires-Dist: py-cord
